{"nodes": [{"id": "home_trashken_carmen_ng_healing_src_pages_testimonials_astro", "label": "testimonials.astro", "file_type": "code", "source_file": "src/pages/testimonials.astro", "source_location": "L1"}, {"id": "pages_testimonials_repeat", "label": "repeat()", "file_type": "code", "source_file": "src/pages/testimonials.astro", "source_location": "L113"}, {"id": "home_trashken_carmen_ng_healing_src_layouts_layout_astro", "label": "../layouts/Layout.astro", "file_type": "code", "source_file": "src/layouts/Layout.astro", "confidence": "EXTRACTED"}, {"id": "astro_content", "label": "astro:content", "file_type": "code", "source_file": "astro:content", "confidence": "EXTRACTED"}], "edges": [{"source": "home_trashken_carmen_ng_healing_src_pages_testimonials_astro", "target": "astro_content", "relation": "imports_from", "context": "import", "confidence": "EXTRACTED", "source_file": "src/pages/testimonials.astro", "source_location": "L3", "weight": 1.0}, {"source": "home_trashken_carmen_ng_healing_src_pages_testimonials_astro", "target": "pages_testimonials_repeat", "relation": "contains", "confidence": "EXTRACTED", "source_file": "src/pages/testimonials.astro", "source_location": "L113", "weight": 1.0}, {"source": "home_trashken_carmen_ng_healing_src_pages_testimonials_astro", "target": "home_trashken_carmen_ng_healing_src_layouts_layout_astro", "relation": "imports_from", "confidence": "EXTRACTED", "source_file": "src/pages/testimonials.astro"}, {"source": "home_trashken_carmen_ng_healing_src_pages_testimonials_astro", "target": "astro_content", "relation": "imports_from", "confidence": "EXTRACTED", "source_file": "src/pages/testimonials.astro"}], "raw_calls": []}